{
    "table": {
        "name": "dbo.ControlPanel",
        "alias": "cntrlpnl"
    },
    "columns": [
        {
              "name": "TerminalName"
            , "type": "nvarchar"
            , "primaryKey": true
        }
        , {
              "name": "SettingName"
            , "type": "nvarchar"
            , "primaryKey": true
        }
        , {
              "name": "DataType"
            , "type": "nvarchar"
        }
        , {
              "name": "DefaultSetting"
            , "type": "nvarchar"
        }
        , {
              "name": "SettingValue"
            , "type": "nvarchar"
        }
        , {
              "name": "Description"
            , "type": "nvarchar"
        }
        , {
              "name": "Fixed"
            , "type": "bit"
        }
        , {
              "name": "CreatedDate"
            , "type": "datetime"
        }
    ]
}